School/DigtCircuit/Verilog/LS74/LS74.v
module LS74 (
    input wire CLR,
    input wire SET,
    input wire CP,
    input wire D,
    output wire Q,
    output wire Qn);
//功能定义
wire g3, g4, g5, g6;
assign g6 = ~( CLR &D &g4);
assign g5 = ~( SET &g6 & g3);
assign g3 = ~( CLR &CP &g5);
assign g4 = ~( g3 &CP &g6);
assign Q = ~( SET &Qn &g3);
assign Qn = ~( CLR &Q &g4);
endmodule

School/DigtCircuit/Verilog/LS74/LS74_tb.v
`timescale 1ns/10ps
module LS74_tb;
reg CLR, SET, CP, D;
wire Q, Qn;
LS74 DUT(
    .CLR(CLR),
    .SET(SET),
    .CP(CP),
    .D(D),
    .Q(Q),
    .Qn(Qn));
initial begin
    CLR = 1'b1; SET = 1'b1; CP = 1'b0; D = 1'b0;
#10 CLR = 1'b1; SET = 1'b1; CP = 1'b1; D = 1'b1;
#10 CLR = 1'b1; SET = 1'b1; CP = 1'b0; D = 1'b1;
#10 CLR = 1'b1; SET = 1'b1; CP = 1'b1; D = 1'b1;
#10 CLR = 1'b1; SET = 1'b1; CP = 1'b0; D = 1'b0;
#10 CLR = 1'b1; SET = 1'b1; CP = 1'b1; D = 1'b0;
#10 CLR = 1'b1; SET = 1'b1; CP = 1'b0; D = 1'b0;
#10 CLR = 1'b1; SET = 1'b1; CP = 1'b1; D = 1'b0;
#10 CLR = 1'b1; SET = 1'b1; CP = 1'b0; D = 1'b0;
end

initial begin
    $dumpfile("LS74_tb.vcd");
    $dumpvars(0, LS74_tb);
    #90 $stop;
end
endmodule

School/DigtCircuit/Verilog/LS74/LS74_tb.vcd
$date
	Mon May  6 13:06:54 2024
$end
$version
	Icarus Verilog
$end
$timescale
	10ps
$end
$scope module LS74_tb $end
$var wire 1 ! Qn $end
$var wire 1 " Q $end
$var reg 1 # CLR $end
$var reg 1 $ CP $end
$var reg 1 % D $end
$var reg 1 & SET $end
$scope module DUT $end
$var wire 1 # CLR $end
$var wire 1 $ CP $end
$var wire 1 % D $end
$var wire 1 " Q $end
$var wire 1 ! Qn $end
$var wire 1 & SET $end
$var wire 1 ' g3 $end
$var wire 1 ( g4 $end
$var wire 1 ) g5 $end
$var wire 1 * g6 $end
$upscope $end
$upscope $end
$enddefinitions $end
#0
$dumpvars
1*
0)
1(
1'
1&
0%
0$
1#
x"
x!
$end
#1000
0'
1"
1)
0!
0*
1(
1%
1$
#2000
1'
0$
#3000
0'
1$
#4000
0)
1*
1'
0%
0$
#5000
0"
1!
0(
1$
#6000
1(
0$
#7000
0(
1$
#8000
1(
0$
