School/DigtCircuit/Verilog/encoder8_3/encoder8_3.v
module encoder8_3(
    input A0,
    input A1,
    input A2,
    input A3,
    input A4,
    input A5,
    input A6,
    input A7,
    output Y0,
    output Y1,
    output Y2);
    assign Y0 = ~(A0 & A2 & A4 & A6);
    assign Y1 = ~(A0 & A1 & A4 & A5);
    assign Y2 = ~(A0 & A1 & A2 & A3); 
endmodule

School/DigtCircuit/Verilog/encoder8_3/encoder8_3_tb.v
`timescale 10ps/1ps
module encoder8_3_tb;
reg [7:0] A;
wire Y0, Y1, Y2;
reg [2:0] i;
encoder8_3 DUT(
    .A0(A[0]),
    .A1(A[1]),
    .A2(A[2]),
    .A3(A[3]),
    .A4(A[4]),
    .A5(A[5]),
    .A6(A[6]),
    .A7(A[7]),
    .Y0(Y0),
    .Y1(Y1),
    .Y2(Y2));
initial begin
    for(i = 0; i <= 7; i = i+1)
    begin
        A = 8'b11111111;
        A[i] = 0; #1;
    end
end

initial begin
    $dumpfile("encoder8_3.vcd");
    $dumpvars(0, encoder8_3_tb);
    #20 $stop;
end
endmodule

School/DigtCircuit/Verilog/encoder8_3/encoder8_3.vcd
$date
	Tue Apr 23 21:24:01 2024
$end
$version
	Icarus Verilog
$end
$timescale
	1ps
$end
$scope module encoder8_3_tb $end
$var wire 1 ! Y2 $end
$var wire 1 " Y1 $end
$var wire 1 # Y0 $end
$var reg 8 $ A [7:0] $end
$var reg 3 % i [2:0] $end
$scope module DUT $end
$var wire 1 & A0 $end
$var wire 1 ' A1 $end
$var wire 1 ( A2 $end
$var wire 1 ) A3 $end
$var wire 1 * A4 $end
$var wire 1 + A5 $end
$var wire 1 , A6 $end
$var wire 1 - A7 $end
$var wire 1 # Y0 $end
$var wire 1 " Y1 $end
$var wire 1 ! Y2 $end
$upscope $end
$upscope $end
$enddefinitions $end
#0
$dumpvars
1-
1,
1+
1*
1)
1(
1'
0&
b0 %
b11111110 $
1#
1"
1!
$end
#10
0#
0'
1&
b11111101 $
b1 %
#20
1#
0"
0(
1'
b11111011 $
b10 %
#30
0#
0)
1(
b11110111 $
b11 %
#40
1#
1"
0!
0*
1)
b11101111 $
b100 %
#50
0#
0+
1*
b11011111 $
b101 %
#60
1#
0"
0,
1+
b10111111 $
b110 %
#70
0#
0-
1,
b1111111 $
b111 %
#80
1#
1"
1!
0&
1-
b11111110 $
b0 %
#90
0#
0'
1&
b11111101 $
b1 %
#100
1#
0"
0(
1'
b11111011 $
b10 %
#110
0#
0)
1(
b11110111 $
b11 %
#120
1#
1"
0!
0*
1)
b11101111 $
b100 %
#130
0#
0+
1*
b11011111 $
b101 %
#140
1#
0"
0,
1+
b10111111 $
b110 %
#150
0#
0-
1,
b1111111 $
b111 %
#160
1#
1"
1!
0&
1-
b11111110 $
b0 %
#170
0#
0'
1&
b11111101 $
b1 %
#180
1#
0"
0(
1'
b11111011 $
b10 %
#190
0#
0)
1(
b11110111 $
b11 %
