School/DigtCircuit/Verilog/LS138/LS138.v
 module LS138 (
    input wire G2A,
    input wire G2B,
    input wire G1,
    input wire A0,
    input wire A1,
    input wire A2,
    output wire Y7,
    output wire Y6,
    output wire Y5,
    output wire Y4,
    output wire Y3,
    output wire Y2,
    output wire Y1,
    output wire Y0);
wire A0n, A1n, A2n;
wire A0nn, A1nn, A2nn, GEn;
assign A0n = ~A0;
assign A0nn = ~A0n;
assign A1n = ~A1;
assign A1nn = ~A1n;
assign A2n = ~A2;
assign A2nn = ~A2n;
assign GEn = G1 & (~G2A) & (~G2B);

assign Y0 = ~(GEn & A2n & A1n & A0n);
assign Y1 = ~(GEn & A2n & A1n & A0nn);
assign Y2 = ~(GEn & A2n & A1nn & A0n);
assign Y3 = ~(GEn & A2n & A1nn & A0nn);
assign Y4 = ~(GEn & A2nn & A1n & A0n);
assign Y5 = ~(GEn & A2nn & A1n & A0nn);
assign Y6 = ~(GEn & A2nn & A1nn & A0n);
assign Y7 = ~(GEn & A2nn & A1nn & A0nn);
 endmodule

School/DigtCircuit/Verilog/LS138/LS138_tb.v
`timescale 1ns/100ps
module LS138_tb;
reg G1, G2A, G2B, A2, A1, A0;
wire Y0, Y1, Y2, Y3, Y4, Y5, Y6, Y7;
LS138 DUT(
    .G1(G1),
    .G2A(G2A),
    .G2B(G2B),
    .A2(A2),
    .A1(A1),
    .A0(A0),
    .Y0(Y0),
    .Y1(Y1),
    .Y2(Y2),
    .Y3(Y3),
    .Y4(Y4),
    .Y5(Y5),
    .Y6(Y6),
    .Y7(Y7));
initial begin
    G1 = 1; G2A = 0; G2B = 0; A2 = 0; A1 = 0; A0 = 0;
#10 G1 = 1; G2A = 0; G2B = 0; A2 = 0; A1 = 0; A0 = 1;
#10 G1 = 1; G2A = 0; G2B = 0; A2 = 0; A1 = 1; A0 = 0;
#10 G1 = 1; G2A = 0; G2B = 0; A2 = 0; A1 = 1; A0 = 1;
#10 G1 = 1; G2A = 0; G2B = 0; A2 = 1; A1 = 0; A0 = 0;
#10 G1 = 1; G2A = 0; G2B = 0; A2 = 1; A1 = 0; A0 = 1;
#10 G1 = 1; G2A = 0; G2B = 0; A2 = 1; A1 = 1; A0 = 0;
#10 G1 = 1; G2A = 0; G2B = 0; A2 = 1; A1 = 1; A0 = 1;
end
initial begin
    $dumpfile("LS138.vcd");
    $dumpvars(0, LS138_tb);
    #80 $stop;
end
endmodule

School/DigtCircuit/Verilog/LS138/LS138.vcd
$date
	Sun Apr 28 23:59:10 2024
$end
$version
	Icarus Verilog
$end
$timescale
	100ps
$end
$scope module LS138_tb $end
$var wire 1 ! Y7 $end
$var wire 1 " Y6 $end
$var wire 1 # Y5 $end
$var wire 1 $ Y4 $end
$var wire 1 % Y3 $end
$var wire 1 & Y2 $end
$var wire 1 ' Y1 $end
$var wire 1 ( Y0 $end
$var reg 1 ) A0 $end
$var reg 1 * A1 $end
$var reg 1 + A2 $end
$var reg 1 , G1 $end
$var reg 1 - G2A $end
$var reg 1 . G2B $end
$scope module DUT $end
$var wire 1 ) A0 $end
$var wire 1 / A0n $end
$var wire 1 0 A0nn $end
$var wire 1 * A1 $end
$var wire 1 1 A1n $end
$var wire 1 2 A1nn $end
$var wire 1 + A2 $end
$var wire 1 3 A2n $end
$var wire 1 4 A2nn $end
$var wire 1 , G1 $end
$var wire 1 - G2A $end
$var wire 1 . G2B $end
$var wire 1 5 GEn $end
$var wire 1 ( Y0 $end
$var wire 1 ' Y1 $end
$var wire 1 & Y2 $end
$var wire 1 % Y3 $end
$var wire 1 $ Y4 $end
$var wire 1 # Y5 $end
$var wire 1 " Y6 $end
$var wire 1 ! Y7 $end
$upscope $end
$upscope $end
$enddefinitions $end
#0
$dumpvars
15
04
13
02
11
00
1/
0.
0-
1,
0+
0*
0)
0(
1'
1&
1%
1$
1#
1"
1!
$end
#100
0'
1(
10
0/
1)
#200
0&
1'
00
12
1/
01
0)
1*
#300
0%
1&
10
0/
1)
#400
0$
1%
1&
00
02
14
1/
11
03
0)
0*
1+
#500
0#
1$
10
0/
1)
#600
0"
1#
00
12
1/
01
0)
1*
#700
0!
1"
10
0/
1)
